[
    {
        "id": 1,
        "nombre": "nombre test",
        "apellido": "apellido test",
        "usuario": "usuariotest",
        "email": "emailtest@emailtest.com",
        "nacimiento": "1977-03-10",
        "domicilio": "test domicilio",
        "pais": "test pais",
        "password1": "test pass 1",
        "password2": "test pass 2",
        "categoria": "general"
    },
    {
        "id": 2,
        "nombre": "Eusebio",
        "apellido": "Gomez",
        "usuario": "chevogomez",
        "email": "chevogomez@gmail.com",
        "nacimiento": "1977-03-10",
        "domicilio": "Lago de Ecatepec #210, Reynosa, Tamaulipas",
        "pais": "MX",
        "password1": "chevo",
        "password2": "chevo",
        "categoria": "general"
    },
    {
        "id": 3,
        "nombre": "Eusebio",
        "apellido": "Gomez",
        "usuario": "chevogomez",
        "email": "chevogomez2@gmail.com",
        "nacimiento": "1977-03-10",
        "domicilio": "Lago de Ecatepec #210, Reynosa, Tamaulipas",
        "pais": "MX",
        "password1": "chevo",
        "password2": "chevo",
        "categoria": "general"
    },
    {
        "id": 4,
        "nombre": "Sylvester ",
        "apellido": "Stallone",
        "usuario": "sylverster",
        "email": "sylvester@hotmail.com",
        "nacimiento": "1960-01-10",
        "domicilio": "Beverly Hills 50210",
        "pais": "US",
        "password1": "pass1",
        "password2": "pass1",
        "categoria": "general"
    },
    {
        "id": 5,
        "nombre": "John",
        "apellido": "Doe",
        "usuario": "johndoe",
        "email": "johndoe@gmail.com",
        "nacimiento": "1987-04-06",
        "domicilio": "Cll 152 # 55 A 10",
        "pais": "CO",
        "password1": "password",
        "password2": "password",
        "categoria": "general"
    },
    {
        "id": 6,
        "nombre": "Mauricio",
        "apellido": "Garces",
        "usuario": "mauri",
        "email": "mauri@hotmail.com",
        "nacimiento": "1970-04-01",
        "domicilio": "Lago Yuriria #123",
        "pais": "MX",
        "password1": "mauricio123",
        "password2": "mauricio123",
        "categoria": "general"
    },
    {
        "id": 7,
        "nombre": "Leonardo",
        "apellido": "DiCaprio",
        "usuario": "leo",
        "email": "leo@leo.com",
        "nacimiento": "2023-08-04",
        "domicilio": "Beverly Hills 123",
        "pais": "US",
        "password1": "123",
        "password2": "123",
        "categoria": "general"
    },
    {
        "id": 8,
        "nombre": "Jane",
        "apellido": "Doe",
        "usuario": "janedoe",
        "email": "janedoe@gmail.com",
        "nacimiento": "1987-04-06",
        "domicilio": "Cr 72 B # 22 A - 90",
        "pais": "DZ",
        "password1": "enigma",
        "password2": "enigma",
        "categoria": "general"
    },
    {
        "id": 9,
        "nombre": "Joe",
        "apellido": "Doe 2",
        "usuario": "johndoe2",
        "email": "johndoe2@gmail.com",
        "nacimiento": "1987-05-06",
        "domicilio": "Avenida de las naciones unidas",
        "pais": "AL",
        "categoria": "general",
        "password1": "$2a$10$oeZrjaDh8qpumdnPQz26VelIFMWjo5rrtCtSJxvlJDT2jYypte7he",
        "password2": "$2a$10$xt4Uz5D0FFxBQxAxkwqMvegSnDpIVNwDFgRXZZKy/wIz2jF/E.sXq"
    },
    {
        "id": 10,
        "nombre": "Tom ",
        "apellido": "Cruise",
        "usuario": "tomcruise",
        "email": "tom@tom.com",
        "nacimiento": "2023-08-17",
        "domicilio": "Beverly Hills 123",
        "pais": "US",
        "categoria": "general",
        "password1": "$2a$10$EY0p5Kmems9T1u/yLgcpVudx9z2MPUiFUNP.eyxU7xaSe4ussBPVu",
        "password2": "$2a$10$54X.Uv0IZmlUeYZ.45MOQ.PdM39XOOuS8.WHB.xz2J5nAwK8CNtWu"
    }
]